acex_driver_cisco_ioscli/__init__.py
acex_driver_cisco_ioscli/cisco_ios_cli.py
acex_driver_cisco_ioscli/filters.py
acex_driver_cisco_ioscli/renderer.py
acex_driver_cisco_ioscli/template.j2
acex_driver_cisco_ioscli-0.0.4.dist-info/METADATA
acex_driver_cisco_ioscli-0.0.4.dist-info/WHEEL
acex_driver_cisco_ioscli-0.0.4.dist-info/entry_points.txt
acex_driver_cisco_ioscli-0.0.4.dist-info/RECORD
