Metadata-Version: 2.4
Name: acex-driver-cisco-ioscli
Version: 0.0.4
Summary: ACE-X Driver: Cisco IOS CLI SSH
License: AGPL-3.0
Author: Johan Lahti
Author-email: johan.lahti@acebit.se
Requires-Python: >=3.13,<4.0
Classifier: License :: OSI Approved :: GNU Affero General Public License v3
Classifier: Programming Language :: Python :: 3
Classifier: Programming Language :: Python :: 3.13
Classifier: Programming Language :: Python :: 3.14
Project-URL: Homepage, https://github.com/acex-labs/acex
Project-URL: Repository, https://github.com/acex-labs/acex
